djangocms_lang_chooser/__init__.py
djangocms_lang_chooser/admin.py
djangocms_lang_chooser/apps.py
djangocms_lang_chooser/cms_plugins.py
djangocms_lang_chooser/models.py
djangocms_lang_chooser/tests.py
djangocms_lang_chooser/views.py
djangocms_lang_chooser/migrations/0001_initial.py
djangocms_lang_chooser/migrations/__init__.py
djangocms_lang_chooser/templates/djangocms_lang_chooser/lang_chooser.html
djangocms_lang_chooser/templates/djangocms_lang_chooser/themes/bootstrap4.html
djangocms_lang_chooser-0.1.0.dist-info/LICENSE
djangocms_lang_chooser-0.1.0.dist-info/METADATA
djangocms_lang_chooser-0.1.0.dist-info/WHEEL
djangocms_lang_chooser-0.1.0.dist-info/top_level.txt
djangocms_lang_chooser-0.1.0.dist-info/RECORD
